deckgljupyter/Layer.py
deckgljupyter/__init__.py
deckgljupyter/templates.py
deckgljupyter/templates/.DS_Store
deckgljupyter/templates/ArcLayer.html
deckgljupyter/templates/GridCellLayer.html
deckgljupyter/templates/GridLayer.html
deckgljupyter/templates/HeatmapLayer.html
deckgljupyter/templates/PathLayer.html
deckgljupyter/templates/PolygonLayer.html
deckgljupyter/templates/ScatterplotLayer.html
deckgljupyter/templates/TripsLayer.html
deckgljupyter/templates/base.html
deckgljupyter/templates/format-utils.js
deckgljupyter/templates/main.html
deckgljupyter/templates/map.html
deckgljupyter-0.1.2.0.dist-info/LICENSE
deckgljupyter-0.1.2.0.dist-info/METADATA
deckgljupyter-0.1.2.0.dist-info/WHEEL
deckgljupyter-0.1.2.0.dist-info/top_level.txt
deckgljupyter-0.1.2.0.dist-info/RECORD
