Metadata-Version: 2.1
Name: deckgljupyter
Version: 0.1.2.0
Summary: Let deck.gl be created in jupyter notebook.
Home-page: https://github.com/heumsi/deckgl-jupyter
Author: heumsi
Author-email: heumsi@naver.com
License: MIT
Download-URL: https://github.com/heumsi/deckgl-jupyter/archive/master.zip
Keywords: deckgl,mapboxgl,location data,visualization
Platform: UNKNOWN
Classifier: Programming Language :: Python :: 3
Classifier: License :: OSI Approved :: MIT License
Requires-Python: >=3
Requires-Dist: mapboxgl
Requires-Dist: jinja2
